{"trial_id": "0045", "hyperparameters": {"space": [{"class_name": "Choice", "config": {"name": "activation", "default": "selu", "conditions": [], "values": ["selu"], "ordered": false}}, {"class_name": "Float", "config": {"name": "lr", "default": 1e-05, "conditions": [], "min_value": 1e-05, "max_value": 0.1, "step": null, "sampling": "log"}}, {"class_name": "Int", "config": {"name": "units_0", "default": null, "conditions": [], "min_value": 30, "max_value": 150, "step": 10, "sampling": "linear"}}, {"class_name": "Float", "config": {"name": "r_k0", "default": 0.01, "conditions": [], "min_value": 0.01, "max_value": 100.0, "step": null, "sampling": "log"}}, {"class_name": "Float", "config": {"name": "r_b0", "default": 0.01, "conditions": [], "min_value": 0.01, "max_value": 100.0, "step": null, "sampling": "log"}}, {"class_name": "Int", "config": {"name": "units_1", "default": null, "conditions": [], "min_value": 30, "max_value": 150, "step": 10, "sampling": "linear"}}, {"class_name": "Float", "config": {"name": "r_k1", "default": 0.01, "conditions": [], "min_value": 0.01, "max_value": 100.0, "step": null, "sampling": "log"}}, {"class_name": "Float", "config": {"name": "r_b1", "default": 0.01, "conditions": [], "min_value": 0.01, "max_value": 100.0, "step": null, "sampling": "log"}}, {"class_name": "Int", "config": {"name": "units_2", "default": null, "conditions": [], "min_value": 30, "max_value": 150, "step": 10, "sampling": "linear"}}, {"class_name": "Float", "config": {"name": "r_k2", "default": 0.01, "conditions": [], "min_value": 0.01, "max_value": 100.0, "step": null, "sampling": "log"}}, {"class_name": "Float", "config": {"name": "r_b2", "default": 0.01, "conditions": [], "min_value": 0.01, "max_value": 100.0, "step": null, "sampling": "log"}}, {"class_name": "Int", "config": {"name": "units_3", "default": null, "conditions": [], "min_value": 30, "max_value": 150, "step": 10, "sampling": "linear"}}, {"class_name": "Float", "config": {"name": "r_k3", "default": 0.01, "conditions": [], "min_value": 0.01, "max_value": 100.0, "step": null, "sampling": "log"}}, {"class_name": "Float", "config": {"name": "r_b3", "default": 0.01, "conditions": [], "min_value": 0.01, "max_value": 100.0, "step": null, "sampling": "log"}}, {"class_name": "Int", "config": {"name": "units_4", "default": null, "conditions": [], "min_value": 30, "max_value": 150, "step": 10, "sampling": "linear"}}, {"class_name": "Float", "config": {"name": "r_k4", "default": 0.01, "conditions": [], "min_value": 0.01, "max_value": 100.0, "step": null, "sampling": "log"}}, {"class_name": "Float", "config": {"name": "r_b4", "default": 0.01, "conditions": [], "min_value": 0.01, "max_value": 100.0, "step": null, "sampling": "log"}}], "values": {"activation": "selu", "lr": 0.04817128364196076, "units_0": 40, "r_k0": 1.4836162999349494, "r_b0": 0.3331847476483189, "units_1": 60, "r_k1": 84.99767877388571, "r_b1": 0.032378715727163984, "units_2": 110, "r_k2": 5.023126914054076, "r_b2": 88.01242297709359, "units_3": 50, "r_k3": 0.11293426204736305, "r_b3": 1.0454029566548055, "units_4": 70, "r_k4": 19.729137420600576, "r_b4": 0.2177292775755808, "tuner/epochs": 2, "tuner/initial_epoch": 0, "tuner/bracket": 2, "tuner/round": 0}}, "metrics": {"metrics": {"loss": {"direction": "min", "observations": [{"value": [358145760.0], "step": 1}]}, "RSquare": {"direction": "min", "observations": [{"value": [0.5520211458206177], "step": 1}]}, "mean_absolute_error": {"direction": "min", "observations": [{"value": [14967.8818359375], "step": 1}]}, "root_mean_squared_error": {"direction": "min", "observations": [{"value": [18922.97265625], "step": 1}]}, "mean_absolute_percentage_error": {"direction": "min", "observations": [{"value": [18.121267318725586], "step": 1}]}, "val_loss": {"direction": "min", "observations": [{"value": [327036032.0], "step": 1}]}, "val_RSquare": {"direction": "min", "observations": [{"value": [0.6280872821807861], "step": 1}]}, "val_mean_absolute_error": {"direction": "min", "observations": [{"value": [13004.94140625], "step": 1}]}, "val_root_mean_squared_error": {"direction": "min", "observations": [{"value": [18082.03125], "step": 1}]}, "val_mean_absolute_percentage_error": {"direction": "min", "observations": [{"value": [18.73531150817871], "step": 1}]}}}, "score": 18082.03125, "best_step": 1, "status": "COMPLETED", "message": null}