{"trial_id": "0008", "hyperparameters": {"space": [{"class_name": "Choice", "config": {"name": "activation", "default": "relu", "conditions": [], "values": ["relu", "tanh", "selu"], "ordered": false}}, {"class_name": "Int", "config": {"name": "layers", "default": null, "conditions": [], "min_value": 1, "max_value": 10, "step": 1, "sampling": "linear"}}, {"class_name": "Float", "config": {"name": "lr", "default": 0.0001, "conditions": [], "min_value": 0.0001, "max_value": 0.01, "step": null, "sampling": "log"}}, {"class_name": "Int", "config": {"name": "units_0", "default": null, "conditions": [], "min_value": 5, "max_value": 250, "step": 5, "sampling": "linear"}}, {"class_name": "Float", "config": {"name": "r_k0", "default": 1e-06, "conditions": [], "min_value": 1e-06, "max_value": 0.01, "step": null, "sampling": "log"}}, {"class_name": "Float", "config": {"name": "r_b0", "default": 1e-06, "conditions": [], "min_value": 1e-06, "max_value": 0.01, "step": null, "sampling": "log"}}, {"class_name": "Int", "config": {"name": "units_1", "default": null, "conditions": [], "min_value": 5, "max_value": 250, "step": 5, "sampling": "linear"}}, {"class_name": "Float", "config": {"name": "r_k1", "default": 1e-06, "conditions": [], "min_value": 1e-06, "max_value": 0.01, "step": null, "sampling": "log"}}, {"class_name": "Float", "config": {"name": "r_b1", "default": 1e-06, "conditions": [], "min_value": 1e-06, "max_value": 0.01, "step": null, "sampling": "log"}}, {"class_name": "Int", "config": {"name": "units_2", "default": null, "conditions": [], "min_value": 5, "max_value": 250, "step": 5, "sampling": "linear"}}, {"class_name": "Float", "config": {"name": "r_k2", "default": 1e-06, "conditions": [], "min_value": 1e-06, "max_value": 0.01, "step": null, "sampling": "log"}}, {"class_name": "Float", "config": {"name": "r_b2", "default": 1e-06, "conditions": [], "min_value": 1e-06, "max_value": 0.01, "step": null, "sampling": "log"}}, {"class_name": "Int", "config": {"name": "units_3", "default": null, "conditions": [], "min_value": 5, "max_value": 250, "step": 5, "sampling": "linear"}}, {"class_name": "Float", "config": {"name": "r_k3", "default": 1e-06, "conditions": [], "min_value": 1e-06, "max_value": 0.01, "step": null, "sampling": "log"}}, {"class_name": "Float", "config": {"name": "r_b3", "default": 1e-06, "conditions": [], "min_value": 1e-06, "max_value": 0.01, "step": null, "sampling": "log"}}, {"class_name": "Int", "config": {"name": "units_4", "default": null, "conditions": [], "min_value": 5, "max_value": 250, "step": 5, "sampling": "linear"}}, {"class_name": "Float", "config": {"name": "r_k4", "default": 1e-06, "conditions": [], "min_value": 1e-06, "max_value": 0.01, "step": null, "sampling": "log"}}, {"class_name": "Float", "config": {"name": "r_b4", "default": 1e-06, "conditions": [], "min_value": 1e-06, "max_value": 0.01, "step": null, "sampling": "log"}}, {"class_name": "Int", "config": {"name": "units_5", "default": null, "conditions": [], "min_value": 5, "max_value": 250, "step": 5, "sampling": "linear"}}, {"class_name": "Float", "config": {"name": "r_k5", "default": 1e-06, "conditions": [], "min_value": 1e-06, "max_value": 0.01, "step": null, "sampling": "log"}}, {"class_name": "Float", "config": {"name": "r_b5", "default": 1e-06, "conditions": [], "min_value": 1e-06, "max_value": 0.01, "step": null, "sampling": "log"}}, {"class_name": "Int", "config": {"name": "units_6", "default": null, "conditions": [], "min_value": 5, "max_value": 250, "step": 5, "sampling": "linear"}}, {"class_name": "Float", "config": {"name": "r_k6", "default": 1e-06, "conditions": [], "min_value": 1e-06, "max_value": 0.01, "step": null, "sampling": "log"}}, {"class_name": "Float", "config": {"name": "r_b6", "default": 1e-06, "conditions": [], "min_value": 1e-06, "max_value": 0.01, "step": null, "sampling": "log"}}, {"class_name": "Int", "config": {"name": "units_7", "default": null, "conditions": [], "min_value": 5, "max_value": 250, "step": 5, "sampling": "linear"}}, {"class_name": "Float", "config": {"name": "r_k7", "default": 1e-06, "conditions": [], "min_value": 1e-06, "max_value": 0.01, "step": null, "sampling": "log"}}, {"class_name": "Float", "config": {"name": "r_b7", "default": 1e-06, "conditions": [], "min_value": 1e-06, "max_value": 0.01, "step": null, "sampling": "log"}}, {"class_name": "Int", "config": {"name": "units_8", "default": null, "conditions": [], "min_value": 5, "max_value": 250, "step": 5, "sampling": "linear"}}, {"class_name": "Float", "config": {"name": "r_k8", "default": 1e-06, "conditions": [], "min_value": 1e-06, "max_value": 0.01, "step": null, "sampling": "log"}}, {"class_name": "Float", "config": {"name": "r_b8", "default": 1e-06, "conditions": [], "min_value": 1e-06, "max_value": 0.01, "step": null, "sampling": "log"}}], "values": {"activation": "tanh", "layers": 2, "lr": 0.0001661447098557725, "units_0": 175, "r_k0": 2.7046797508603303e-05, "r_b0": 8.499266530062692e-06, "units_1": 25, "r_k1": 0.0033839521004648617, "r_b1": 0.0008278796542982231, "units_2": 195, "r_k2": 1.6620033714641175e-06, "r_b2": 0.004810524783907691, "units_3": 240, "r_k3": 0.0020114111535770277, "r_b3": 0.0077607461145708075, "units_4": 25, "r_k4": 0.0037187535099586595, "r_b4": 8.018049288865912e-06, "units_5": 210, "r_k5": 1.7465257492496662e-06, "r_b5": 0.0005335102842529536, "units_6": 80, "r_k6": 0.0004565787311657388, "r_b6": 0.0020320852667545532, "units_7": 195, "r_k7": 0.00030399430728374384, "r_b7": 9.994395178758984e-06, "units_8": 135, "r_k8": 3.695277732998534e-05, "r_b8": 1.6003565622789292e-06, "tuner/epochs": 7, "tuner/initial_epoch": 0, "tuner/bracket": 2, "tuner/round": 0}}, "metrics": {"metrics": {"loss": {"direction": "min", "observations": [{"value": [9910680576.0], "step": 6}]}, "mean_absolute_error": {"direction": "min", "observations": [{"value": [95385.15625], "step": 6}]}, "root_mean_squared_error": {"direction": "min", "observations": [{"value": [99552.40625], "step": 6}]}, "mean_absolute_percentage_error": {"direction": "min", "observations": [{"value": [99.9857406616211], "step": 6}]}, "val_loss": {"direction": "min", "observations": [{"value": [9659018240.0], "step": 6}]}, "val_mean_absolute_error": {"direction": "min", "observations": [{"value": [93982.7734375], "step": 6}]}, "val_root_mean_squared_error": {"direction": "min", "observations": [{"value": [98280.3046875], "step": 6}]}, "val_mean_absolute_percentage_error": {"direction": "min", "observations": [{"value": [99.98486328125], "step": 6}]}}}, "score": 99552.40625, "best_step": 6, "status": "COMPLETED", "message": null}