{"trial_id": "0035", "hyperparameters": {"space": [{"class_name": "Choice", "config": {"name": "activation", "default": "selu", "conditions": [], "values": ["selu"], "ordered": false}}, {"class_name": "Float", "config": {"name": "lr", "default": 1e-05, "conditions": [], "min_value": 1e-05, "max_value": 0.1, "step": null, "sampling": "log"}}, {"class_name": "Int", "config": {"name": "units_0", "default": null, "conditions": [], "min_value": 30, "max_value": 150, "step": 10, "sampling": "linear"}}, {"class_name": "Float", "config": {"name": "r_k0", "default": 0.01, "conditions": [], "min_value": 0.01, "max_value": 100.0, "step": null, "sampling": "log"}}, {"class_name": "Float", "config": {"name": "r_b0", "default": 0.01, "conditions": [], "min_value": 0.01, "max_value": 100.0, "step": null, "sampling": "log"}}, {"class_name": "Int", "config": {"name": "units_1", "default": null, "conditions": [], "min_value": 30, "max_value": 150, "step": 10, "sampling": "linear"}}, {"class_name": "Float", "config": {"name": "r_k1", "default": 0.01, "conditions": [], "min_value": 0.01, "max_value": 100.0, "step": null, "sampling": "log"}}, {"class_name": "Float", "config": {"name": "r_b1", "default": 0.01, "conditions": [], "min_value": 0.01, "max_value": 100.0, "step": null, "sampling": "log"}}, {"class_name": "Int", "config": {"name": "units_2", "default": null, "conditions": [], "min_value": 30, "max_value": 150, "step": 10, "sampling": "linear"}}, {"class_name": "Float", "config": {"name": "r_k2", "default": 0.01, "conditions": [], "min_value": 0.01, "max_value": 100.0, "step": null, "sampling": "log"}}, {"class_name": "Float", "config": {"name": "r_b2", "default": 0.01, "conditions": [], "min_value": 0.01, "max_value": 100.0, "step": null, "sampling": "log"}}, {"class_name": "Int", "config": {"name": "units_3", "default": null, "conditions": [], "min_value": 30, "max_value": 150, "step": 10, "sampling": "linear"}}, {"class_name": "Float", "config": {"name": "r_k3", "default": 0.01, "conditions": [], "min_value": 0.01, "max_value": 100.0, "step": null, "sampling": "log"}}, {"class_name": "Float", "config": {"name": "r_b3", "default": 0.01, "conditions": [], "min_value": 0.01, "max_value": 100.0, "step": null, "sampling": "log"}}, {"class_name": "Int", "config": {"name": "units_4", "default": null, "conditions": [], "min_value": 30, "max_value": 150, "step": 10, "sampling": "linear"}}, {"class_name": "Float", "config": {"name": "r_k4", "default": 0.01, "conditions": [], "min_value": 0.01, "max_value": 100.0, "step": null, "sampling": "log"}}, {"class_name": "Float", "config": {"name": "r_b4", "default": 0.01, "conditions": [], "min_value": 0.01, "max_value": 100.0, "step": null, "sampling": "log"}}], "values": {"activation": "selu", "lr": 6.542744258561446e-05, "units_0": 140, "r_k0": 64.62119328996246, "r_b0": 0.013271712160717609, "units_1": 100, "r_k1": 13.597604139954306, "r_b1": 0.02576424193245698, "units_2": 150, "r_k2": 0.20296306989857363, "r_b2": 28.011598708577754, "units_3": 50, "r_k3": 0.023670602557736974, "r_b3": 0.559471378179611, "units_4": 100, "r_k4": 1.5167062861780094, "r_b4": 0.0149365752402054, "tuner/epochs": 2, "tuner/initial_epoch": 0, "tuner/bracket": 2, "tuner/round": 0}}, "metrics": {"metrics": {"loss": {"direction": "min", "observations": [{"value": [9992848384.0], "step": 1}]}, "mean_absolute_error": {"direction": "min", "observations": [{"value": [95883.0234375], "step": 1}]}, "root_mean_squared_error": {"direction": "min", "observations": [{"value": [99964.2109375], "step": 1}]}, "mean_absolute_percentage_error": {"direction": "min", "observations": [{"value": [99.99600982666016], "step": 1}]}, "val_loss": {"direction": "min", "observations": [{"value": [9210268672.0], "step": 1}]}, "val_mean_absolute_error": {"direction": "min", "observations": [{"value": [91275.296875], "step": 1}]}, "val_root_mean_squared_error": {"direction": "min", "observations": [{"value": [95970.1171875], "step": 1}]}, "val_mean_absolute_percentage_error": {"direction": "min", "observations": [{"value": [99.99388122558594], "step": 1}]}}}, "score": 95970.1171875, "best_step": 1, "status": "COMPLETED", "message": null}