{"trial_id": "0112", "hyperparameters": {"space": [{"class_name": "Choice", "config": {"name": "activation", "default": "selu", "conditions": [], "values": ["selu"], "ordered": false}}, {"class_name": "Float", "config": {"name": "lr", "default": 1e-05, "conditions": [], "min_value": 1e-05, "max_value": 0.1, "step": null, "sampling": "log"}}, {"class_name": "Int", "config": {"name": "units_0", "default": null, "conditions": [], "min_value": 30, "max_value": 150, "step": 10, "sampling": "linear"}}, {"class_name": "Float", "config": {"name": "r_k0", "default": 0.01, "conditions": [], "min_value": 0.01, "max_value": 100.0, "step": null, "sampling": "log"}}, {"class_name": "Float", "config": {"name": "r_b0", "default": 0.01, "conditions": [], "min_value": 0.01, "max_value": 100.0, "step": null, "sampling": "log"}}, {"class_name": "Int", "config": {"name": "units_1", "default": null, "conditions": [], "min_value": 30, "max_value": 150, "step": 10, "sampling": "linear"}}, {"class_name": "Float", "config": {"name": "r_k1", "default": 0.01, "conditions": [], "min_value": 0.01, "max_value": 100.0, "step": null, "sampling": "log"}}, {"class_name": "Float", "config": {"name": "r_b1", "default": 0.01, "conditions": [], "min_value": 0.01, "max_value": 100.0, "step": null, "sampling": "log"}}, {"class_name": "Int", "config": {"name": "units_2", "default": null, "conditions": [], "min_value": 30, "max_value": 150, "step": 10, "sampling": "linear"}}, {"class_name": "Float", "config": {"name": "r_k2", "default": 0.01, "conditions": [], "min_value": 0.01, "max_value": 100.0, "step": null, "sampling": "log"}}, {"class_name": "Float", "config": {"name": "r_b2", "default": 0.01, "conditions": [], "min_value": 0.01, "max_value": 100.0, "step": null, "sampling": "log"}}, {"class_name": "Int", "config": {"name": "units_3", "default": null, "conditions": [], "min_value": 30, "max_value": 150, "step": 10, "sampling": "linear"}}, {"class_name": "Float", "config": {"name": "r_k3", "default": 0.01, "conditions": [], "min_value": 0.01, "max_value": 100.0, "step": null, "sampling": "log"}}, {"class_name": "Float", "config": {"name": "r_b3", "default": 0.01, "conditions": [], "min_value": 0.01, "max_value": 100.0, "step": null, "sampling": "log"}}, {"class_name": "Int", "config": {"name": "units_4", "default": null, "conditions": [], "min_value": 30, "max_value": 150, "step": 10, "sampling": "linear"}}, {"class_name": "Float", "config": {"name": "r_k4", "default": 0.01, "conditions": [], "min_value": 0.01, "max_value": 100.0, "step": null, "sampling": "log"}}, {"class_name": "Float", "config": {"name": "r_b4", "default": 0.01, "conditions": [], "min_value": 0.01, "max_value": 100.0, "step": null, "sampling": "log"}}], "values": {"activation": "selu", "lr": 0.0001866975616946515, "units_0": 110, "r_k0": 0.9019176798870023, "r_b0": 51.406981231782154, "units_1": 60, "r_k1": 17.83894962325514, "r_b1": 6.020613116394867, "units_2": 30, "r_k2": 6.680263086640115, "r_b2": 7.330573911176663, "units_3": 30, "r_k3": 79.64795725983952, "r_b3": 4.945307472801952, "units_4": 130, "r_k4": 0.01637628209986537, "r_b4": 1.9133958700936842, "tuner/epochs": 2, "tuner/initial_epoch": 0, "tuner/bracket": 2, "tuner/round": 0}}, "metrics": {"metrics": {"loss": {"direction": "min", "observations": [{"value": [9992396800.0], "step": 1}]}, "mean_absolute_error": {"direction": "min", "observations": [{"value": [95880.578125], "step": 1}]}, "root_mean_squared_error": {"direction": "min", "observations": [{"value": [99961.953125], "step": 1}]}, "mean_absolute_percentage_error": {"direction": "min", "observations": [{"value": [99.99301147460938], "step": 1}]}, "val_loss": {"direction": "min", "observations": [{"value": [9209577472.0], "step": 1}]}, "val_mean_absolute_error": {"direction": "min", "observations": [{"value": [91271.40625], "step": 1}]}, "val_root_mean_squared_error": {"direction": "min", "observations": [{"value": [95966.53125], "step": 1}]}, "val_mean_absolute_percentage_error": {"direction": "min", "observations": [{"value": [99.98880004882812], "step": 1}]}}}, "score": 95966.53125, "best_step": 1, "status": "COMPLETED", "message": null}